ezollama.py
ezollama-0.2.1.dist-info/licenses/LICENSE
ezollama-0.2.1.dist-info/METADATA
ezollama-0.2.1.dist-info/WHEEL
ezollama-0.2.1.dist-info/top_level.txt
ezollama-0.2.1.dist-info/RECORD
