Metadata-Version: 2.4
Name: ezollama
Version: 0.2.1
Summary: A lightweight Python wrapper for Ollama AI models.
Author-email: SuperKaa <you@example.com>
License: MIT
Requires-Python: >=3.10
License-File: LICENSE
Requires-Dist: requests>=2.28
Requires-Dist: pyttsx3>=2.90
Dynamic: license-file
